welllog_ui/__init__.py
welllog_ui/__main__.cp39-win_amd64.pyd
welllog_ui/__main__.pyi
welllog_ui/config.cp39-win_amd64.pyd
welllog_ui/config.pyi
welllog_ui/database_project_dialog.cp39-win_amd64.pyd
welllog_ui/database_project_dialog.pyi
welllog_ui/libPyBO39.pyd
welllog_ui/libPyBO39.pyi
welllog_ui/main_V2.cp39-win_amd64.pyd
welllog_ui/main_V2.pyi
welllog_ui/test.cp39-win_amd64.pyd
welllog_ui/test.pyi
welllog_ui/services/__init__.py
welllog_ui/services/bowells_service.cp39-win_amd64.pyd
welllog_ui/services/bowells_service.pyi
welllog_ui/services/db.cp39-win_amd64.pyd
welllog_ui/services/db.pyi
welllog_ui/tools/__init__.py
welllog_ui/tools/base_plugin.cp39-win_amd64.pyd
welllog_ui/tools/base_plugin.pyi
welllog_ui/tools/dl/__init__.py
welllog_ui/tools/dl/base_dl.cp39-win_amd64.pyd
welllog_ui/tools/dl/base_dl.pyi
welllog_ui/tools/dl/cfg.cp39-win_amd64.pyd
welllog_ui/tools/dl/cfg.pyi
welllog_ui/tools/dl/components.cp39-win_amd64.pyd
welllog_ui/tools/dl/components.pyi
welllog_ui/tools/dl/model.cp39-win_amd64.pyd
welllog_ui/tools/dl/model.pyi
welllog_ui/tools/dl/quantizers.cp39-win_amd64.pyd
welllog_ui/tools/dl/quantizers.pyi
welllog_ui/tools/dl/trainer_worker.cp39-win_amd64.pyd
welllog_ui/tools/dl/trainer_worker.pyi
welllog_ui/tools/dl/WTConv/wavelet_1d.cp39-win_amd64.pyd
welllog_ui/tools/dl/WTConv/wavelet_1d.pyi
welllog_ui/tools/dl/WTConv/wtconv1d.cp39-win_amd64.pyd
welllog_ui/tools/dl/WTConv/wtconv1d.pyi
welllog_ui/tools/dl/data_utils/well_data_utils.cp39-win_amd64.pyd
welllog_ui/tools/dl/data_utils/well_data_utils.pyi
welllog_ui/widgets/__init__.py
welllog_ui/widgets/deep_learning_dialog_ordered.cp39-win_amd64.pyd
welllog_ui/widgets/deep_learning_dialog_ordered.pyi
welllog_ui/widgets/well_curve_plotter_pyqtgraph.cp39-win_amd64.pyd
welllog_ui/widgets/well_curve_plotter_pyqtgraph.pyi
welllog_ui/widgets/well_filter_dialog.cp39-win_amd64.pyd
welllog_ui/widgets/well_filter_dialog.pyi
welllog_ui/widgets/well_selection_dialog_v2.cp39-win_amd64.pyd
welllog_ui-0.0.121.dist-info/METADATA
welllog_ui-0.0.121.dist-info/WHEEL
welllog_ui-0.0.121.dist-info/entry_points.txt
welllog_ui-0.0.121.dist-info/top_level.txt
welllog_ui-0.0.121.dist-info/RECORD
