Metadata-Version: 2.4
Name: welllog_ui
Version: 0.0.121
Summary: WellLog UI with PySide6 and DL pipeline
Author-email: wxiong_swpu <1305483753@qq.com>
License: Proprietary
Project-URL: Homepage, https://github.com/wxiong_swpu/welllog_ui
Project-URL: Issues, https://github.com/wxiong_swpu/welllog_ui/issues
Classifier: Programming Language :: Python :: 3
Classifier: Programming Language :: Python :: 3.9
Classifier: Operating System :: Microsoft :: Windows
Classifier: Topic :: Scientific/Engineering
Requires-Python: >=3.9
Requires-Dist: PySide6<7,>=6.5
Requires-Dist: numpy
Requires-Dist: torch
Requires-Dist: pytorch-lightning
Requires-Dist: scikit-learn
Requires-Dist: pyqtgraph
Requires-Dist: PyWavelets
Requires-Dist: chardet
